[
  {
    "type": "terrain",
    "id": "t_door_c",
    "copy-from": "t_door_c",
    "bash": {
      "hit_field": [
        "fd_dust",
        0
      ],
      "destroyed_field": [
        "fd_splinters",
        0
      ]
    }
  },
  {
    "type": "terrain",
    "id": "t_door_elocked",
    "copy-from": "t_door_elocked",
    "bash": {
      "hit_field": [
        "fd_dust",
        0
      ],
      "destroyed_field": [
        "fd_splinters",
        0
      ]
    }
  },
  {
    "type": "terrain",
    "id": "t_door_elocked_peep",
    "copy-from": "t_door_elocked_peep",
    "bash": {
      "hit_field": [
        "fd_dust",
        0
      ],
      "destroyed_field": [
        "fd_splinters",
        0
      ]
    }
  },
  {
    "type": "terrain",
    "id": "t_door_elocked_alarm",
    "copy-from": "t_door_elocked_alarm",
    "bash": {
      "hit_field": [
        "fd_dust",
        0
      ],
      "destroyed_field": [
        "fd_splinters",
        0
      ]
    }
  },
  {
    "type": "terrain",
    "id": "t_door_lab_c",
    "copy-from": "t_door_lab_c",
    "bash": {
      "hit_field": [
        "fd_dust",
        0
      ],
      "destroyed_field": [
        "fd_splinters",
        0
      ]
    }
  },
  {
    "type": "terrain",
    "id": "t_door_white_c",
    "copy-from": "t_door_white_c",
    "bash": {
      "hit_field": [
        "fd_dust",
        0
      ],
      "destroyed_field": [
        "fd_splinters",
        0
      ]
    }
  },
  {
    "type": "terrain",
    "id": "t_door_gray_c",
    "copy-from": "t_door_gray_c",
    "bash": {
      "hit_field": [
        "fd_dust",
        0
      ],
      "destroyed_field": [
        "fd_splinters",
        0
      ]
    }
  },
  {
    "type": "terrain",
    "id": "t_door_red_c",
    "copy-from": "t_door_red_c",
    "bash": {
      "hit_field": [
        "fd_dust",
        0
      ],
      "destroyed_field": [
        "fd_splinters",
        0
      ]
    }
  },
  {
    "type": "terrain",
    "id": "t_door_green_c",
    "copy-from": "t_door_green_c",
    "bash": {
      "hit_field": [
        "fd_dust",
        0
      ],
      "destroyed_field": [
        "fd_splinters",
        0
      ]
    }
  },
  {
    "type": "terrain",
    "id": "t_door_white_o",
    "copy-from": "t_door_white_o",
    "bash": {
      "hit_field": [
        "fd_dust",
        0
      ],
      "destroyed_field": [
        "fd_splinters",
        0
      ]
    }
  },
  {
    "type": "terrain",
    "id": "t_door_gray_o",
    "copy-from": "t_door_gray_o",
    "bash": {
      "hit_field": [
        "fd_dust",
        0
      ],
      "destroyed_field": [
        "fd_splinters",
        0
      ]
    }
  },
  {
    "type": "terrain",
    "id": "t_door_red_o",
    "copy-from": "t_door_red_o",
    "bash": {
      "hit_field": [
        "fd_dust",
        0
      ],
      "destroyed_field": [
        "fd_splinters",
        0
      ]
    }
  },
  {
    "type": "terrain",
    "id": "t_door_green_o",
    "copy-from": "t_door_green_o",
    "bash": {
      "hit_field": [
        "fd_dust",
        0
      ],
      "destroyed_field": [
        "fd_splinters",
        0
      ]
    }
  },
  {
    "type": "terrain",
    "id": "t_door_white_b",
    "copy-from": "t_door_white_b",
    "bash": {
      "hit_field": [
        "fd_dust",
        0
      ],
      "destroyed_field": [
        "fd_splinters",
        0
      ]
    }
  },
  {
    "type": "terrain",
    "id": "t_door_gray_b",
    "copy-from": "t_door_gray_b",
    "bash": {
      "hit_field": [
        "fd_dust",
        0
      ],
      "destroyed_field": [
        "fd_splinters",
        0
      ]
    }
  },
  {
    "type": "terrain",
    "id": "t_door_red_b",
    "copy-from": "t_door_red_b",
    "bash": {
      "hit_field": [
        "fd_dust",
        0
      ],
      "destroyed_field": [
        "fd_splinters",
        0
      ]
    }
  },
  {
    "type": "terrain",
    "id": "t_door_green_b",
    "copy-from": "t_door_green_b",
    "bash": {
      "hit_field": [
        "fd_dust",
        0
      ],
      "destroyed_field": [
        "fd_splinters",
        0
      ]
    }
  },
  {
    "type": "terrain",
    "id": "t_door_white_frame",
    "copy-from": "t_door_white_frame",
    "bash": {
      "hit_field": [
        "fd_dust",
        0
      ],
      "destroyed_field": [
        "fd_splinters",
        0
      ]
    }
  },
  {
    "type": "terrain",
    "id": "t_door_gray_frame",
    "copy-from": "t_door_gray_frame",
    "bash": {
      "hit_field": [
        "fd_dust",
        0
      ],
      "destroyed_field": [
        "fd_splinters",
        0
      ]
    }
  },
  {
    "type": "terrain",
    "id": "t_door_red_frame",
    "copy-from": "t_door_red_frame",
    "bash": {
      "hit_field": [
        "fd_dust",
        0
      ],
      "destroyed_field": [
        "fd_splinters",
        0
      ]
    }
  },
  {
    "type": "terrain",
    "id": "t_door_green_frame",
    "copy-from": "t_door_green_frame",
    "bash": {
      "hit_field": [
        "fd_dust",
        0
      ],
      "destroyed_field": [
        "fd_splinters",
        0
      ]
    }
  },
  {
    "type": "terrain",
    "id": "t_door_c_peep",
    "copy-from": "t_door_c_peep",
    "bash": {
      "hit_field": [
        "fd_dust",
        0
      ],
      "destroyed_field": [
        "fd_splinters",
        0
      ]
    }
  },
  {
    "type": "terrain",
    "id": "t_door_b",
    "copy-from": "t_door_b",
    "bash": {
      "hit_field": [
        "fd_dust",
        0
      ],
      "destroyed_field": [
        "fd_splinters",
        0
      ]
    }
  },
  {
    "type": "terrain",
    "id": "t_door_lab_b",
    "copy-from": "t_door_lab_b",
    "bash": {
      "hit_field": [
        "fd_dust",
        0
      ],
      "destroyed_field": [
        "fd_splinters",
        0
      ]
    }
  },
  {
    "type": "terrain",
    "id": "t_door_b_peep",
    "copy-from": "t_door_b_peep",
    "bash": {
      "hit_field": [
        "fd_dust",
        0
      ],
      "destroyed_field": [
        "fd_splinters",
        0
      ]
    }
  },
  {
    "type": "terrain",
    "id": "t_door_o",
    "copy-from": "t_door_o",
    "bash": {
      "hit_field": [
        "fd_dust",
        0
      ],
      "destroyed_field": [
        "fd_splinters",
        0
      ]
    }
  },
  {
    "type": "terrain",
    "id": "t_door_lab_o",
    "copy-from": "t_door_lab_o",
    "bash": {
      "hit_field": [
        "fd_dust",
        0
      ],
      "destroyed_field": [
        "fd_splinters",
        0
      ]
    }
  },
  {
    "type": "terrain",
    "id": "t_door_o_peep",
    "copy-from": "t_door_o_peep",
    "bash": {
      "hit_field": [
        "fd_dust",
        0
      ],
      "destroyed_field": [
        "fd_splinters",
        0
      ]
    }
  },
  {
    "type": "terrain",
    "id": "t_rdoor_c",
    "copy-from": "t_rdoor_c",
    "bash": {
      "hit_field": [
        "fd_dust",
        0
      ],
      "destroyed_field": [
        "fd_splinters",
        0
      ]
    }
  },
  {
    "type": "terrain",
    "id": "t_rdoor_b",
    "copy-from": "t_rdoor_b",
    "bash": {
      "hit_field": [
        "fd_dust",
        0
      ],
      "destroyed_field": [
        "fd_splinters",
        0
      ]
    }
  },
  {
    "type": "terrain",
    "id": "t_rdoor_o",
    "copy-from": "t_rdoor_o",
    "bash": {
      "hit_field": [
        "fd_dust",
        0
      ],
      "destroyed_field": [
        "fd_splinters",
        0
      ]
    }
  },
  {
    "type": "terrain",
    "id": "t_door_locked_interior",
    "copy-from": "t_door_locked_interior",
    "bash": {
      "hit_field": [
        "fd_dust",
        0
      ],
      "destroyed_field": [
        "fd_splinters",
        0
      ]
    }
  },
  {
    "type": "terrain",
    "id": "t_door_locked",
    "copy-from": "t_door_locked",
    "bash": {
      "hit_field": [
        "fd_dust",
        0
      ],
      "destroyed_field": [
        "fd_splinters",
        0
      ]
    }
  },
  {
    "type": "terrain",
    "id": "t_door_locked_peep",
    "copy-from": "t_door_locked_peep",
    "bash": {
      "hit_field": [
        "fd_dust",
        0
      ],
      "destroyed_field": [
        "fd_splinters",
        0
      ]
    }
  },
  {
    "type": "terrain",
    "id": "t_door_locked_alarm",
    "copy-from": "t_door_locked_alarm",
    "bash": {
      "hit_field": [
        "fd_dust",
        0
      ],
      "destroyed_field": [
        "fd_splinters",
        0
      ]
    }
  },
  {
    "type": "terrain",
    "id": "t_door_makeshift_c",
    "copy-from": "t_door_makeshift_c",
    "bash": {
      "hit_field": [
        "fd_dust",
        0
      ],
      "destroyed_field": [
        "fd_splinters",
        0
      ]
    }
  },
  {
    "type": "terrain",
    "id": "t_door_makeshift_o",
    "copy-from": "t_door_makeshift_o",
    "bash": {
      "hit_field": [
        "fd_dust",
        0
      ],
      "destroyed_field": [
        "fd_splinters",
        0
      ]
    }
  },
  {
    "type": "terrain",
    "id": "t_door_frame",
    "copy-from": "t_door_frame",
    "bash": {
      "hit_field": [
        "fd_dust",
        0
      ],
      "destroyed_field": [
        "fd_splinters",
        0
      ]
    }
  },
  {
    "type": "terrain",
    "id": "t_door_lab_frame",
    "copy-from": "t_door_lab_frame",
    "bash": {
      "hit_field": [
        "fd_dust",
        0
      ],
      "destroyed_field": [
        "fd_splinters",
        0
      ]
    }
  },
  {
    "type": "terrain",
    "id": "t_door_boarded",
    "copy-from": "t_door_boarded",
    "bash": {
      "hit_field": [
        "fd_dust",
        0
      ],
      "destroyed_field": [
        "fd_splinters",
        0
      ]
    }
  },
  {
    "type": "terrain",
    "id": "t_door_boarded_damaged",
    "copy-from": "t_door_boarded_damaged",
    "bash": {
      "hit_field": [
        "fd_dust",
        0
      ],
      "destroyed_field": [
        "fd_splinters",
        0
      ]
    }
  },
  {
    "type": "terrain",
    "id": "t_door_boarded_peep",
    "copy-from": "t_door_boarded_peep",
    "bash": {
      "hit_field": [
        "fd_dust",
        0
      ],
      "destroyed_field": [
        "fd_splinters",
        0
      ]
    }
  },
  {
    "type": "terrain",
    "id": "t_rdoor_boarded",
    "copy-from": "t_rdoor_boarded",
    "bash": {
      "hit_field": [
        "fd_dust",
        0
      ],
      "destroyed_field": [
        "fd_splinters",
        0
      ]
    }
  },
  {
    "type": "terrain",
    "id": "t_rdoor_boarded_damaged",
    "copy-from": "t_rdoor_boarded_damaged",
    "bash": {
      "hit_field": [
        "fd_dust",
        0
      ],
      "destroyed_field": [
        "fd_splinters",
        0
      ]
    }
  },
  {
    "type": "terrain",
    "id": "t_door_boarded_damaged_peep",
    "copy-from": "t_door_boarded_damaged_peep",
    "bash": {
      "hit_field": [
        "fd_dust",
        0
      ],
      "destroyed_field": [
        "fd_splinters",
        0
      ]
    }
  }
]