[
  {
    "type": "terrain",
    "id": "t_triffid_bark_wall",
    "copy-from": "t_triffid_bark_wall",
    "bash": {
      "hit_field": [
        "fd_dust",
        0
      ],
      "destroyed_field": [
        "fd_splinters",
        0
      ]
    }
  },
  {
    "type": "terrain",
    "id": "t_bark_wall_chipped",
    "copy-from": "t_bark_wall_chipped",
    "bash": {
      "hit_field": [
        "fd_dust",
        0
      ],
      "destroyed_field": [
        "fd_splinters",
        0
      ]
    }
  },
  {
    "type": "terrain",
    "id": "t_bark_wall_broken",
    "copy-from": "t_bark_wall_broken",
    "bash": {
      "hit_field": [
        "fd_dust",
        0
      ],
      "destroyed_field": [
        "fd_splinters",
        0
      ]
    }
  },
  {
    "type": "terrain",
    "id": "t_triffid_wood_wall",
    "copy-from": "t_triffid_wood_wall",
    "bash": {
      "hit_field": [
        "fd_dust",
        0
      ],
      "destroyed_field": [
        "fd_splinters",
        0
      ]
    }
  },
  {
    "type": "terrain",
    "id": "t_barkfloor",
    "copy-from": "t_barkfloor",
    "bash": {
      "hit_field": [
        "fd_dust",
        0
      ],
      "destroyed_field": [
        "fd_splinters",
        0
      ]
    }
  },
  {
    "type": "terrain",
    "id": "t_barkfloor_noroof",
    "copy-from": "t_barkfloor_noroof",
    "bash": {
      "hit_field": [
        "fd_dust",
        0
      ],
      "destroyed_field": [
        "fd_splinters",
        0
      ]
    }
  },
  {
    "type": "terrain",
    "id": "t_root_floor",
    "copy-from": "t_root_floor",
    "bash": {
      "hit_field": [
        "fd_dust",
        0
      ],
      "destroyed_field": [
        "fd_splinters",
        0
      ]
    }
  },
  {
    "type": "terrain",
    "id": "t_bramble_door_c",
    "copy-from": "t_bramble_door_c",
    "open": "t_bramble_door_o",
    "bash": {
      "hit_field": [
        "fd_dust",
        0
      ],
      "destroyed_field": [
        "fd_splinters",
        0
      ]
    }
  },
  {
    "type": "terrain",
    "id": "t_bramble_door_o",
    "copy-from": "t_bramble_door_o",
    "close": "t_bramble_door_c",
    "bash": {
      "hit_field": [
        "fd_dust",
        0
      ],
      "destroyed_field": [
        "fd_splinters",
        0
      ]
    }
  }
]